<?xml version="1.0" encoding="UTF-8"?>

<scenario:scenario xmlns:scenario="urn:roborescue:map:scenario">
  <scenario:refuge scenario:location="36467"/>
  <scenario:refuge scenario:location="36494"/>
  <scenario:fire scenario:location="28099"/>
  <scenario:fire scenario:location="20469"/>
  <scenario:fire scenario:location="36424"/>
  <scenario:gasstation scenario:location="34723"/>
  <scenario:gasstation scenario:location="31032"/>
  <scenario:civilian scenario:location="26860"/>
  <scenario:civilian scenario:location="30940"/>
  <scenario:civilian scenario:location="36416"/>
  <scenario:civilian scenario:location="36563"/>
  <scenario:civilian scenario:location="28024"/>
  <scenario:civilian scenario:location="24166"/>
  <scenario:civilian scenario:location="36195"/>
  <scenario:civilian scenario:location="24407"/>
  <scenario:civilian scenario:location="31564"/>
  <scenario:civilian scenario:location="18869"/>
  <scenario:civilian scenario:location="36467"/>
  <scenario:civilian scenario:location="21308"/>
  <scenario:civilian scenario:location="18653"/>
  <scenario:civilian scenario:location="36255"/>
  <scenario:civilian scenario:location="30225"/>
  <scenario:civilian scenario:location="36211"/>
  <scenario:civilian scenario:location="31900"/>
  <scenario:civilian scenario:location="26533"/>
  <scenario:civilian scenario:location="22855"/>
  <scenario:civilian scenario:location="16779"/>
  <scenario:civilian scenario:location="36405"/>
  <scenario:civilian scenario:location="32889"/>
  <scenario:civilian scenario:location="36259"/>
  <scenario:civilian scenario:location="22459"/>
  <scenario:civilian scenario:location="21878"/>
  <scenario:civilian scenario:location="31517"/>
  <scenario:civilian scenario:location="23905"/>
  <scenario:civilian scenario:location="36248"/>
  <scenario:civilian scenario:location="30585"/>
  <scenario:civilian scenario:location="36390"/>
  <scenario:civilian scenario:location="30514"/>
  <scenario:civilian scenario:location="17806"/>
  <scenario:civilian scenario:location="36202"/>
  <scenario:civilian scenario:location="23463"/>
  <scenario:civilian scenario:location="36409"/>
  <scenario:civilian scenario:location="36416"/>
  <scenario:civilian scenario:location="25420"/>
  <scenario:civilian scenario:location="36544"/>
  <scenario:civilian scenario:location="32088"/>
  <scenario:civilian scenario:location="31445"/>
  <scenario:civilian scenario:location="24455"/>
  <scenario:civilian scenario:location="16779"/>
  <scenario:civilian scenario:location="30416"/>
  <scenario:civilian scenario:location="36402"/>
  <scenario:civilian scenario:location="34533"/>
  <scenario:civilian scenario:location="36441"/>
  <scenario:civilian scenario:location="22484"/>
  <scenario:civilian scenario:location="33716"/>
  <scenario:civilian scenario:location="23928"/>
  <scenario:civilian scenario:location="16871"/>
  <scenario:civilian scenario:location="28122"/>
  <scenario:civilian scenario:location="36272"/>
  <scenario:civilian scenario:location="33766"/>
  <scenario:civilian scenario:location="17250"/>
  <scenario:civilian scenario:location="33793"/>
  <scenario:civilian scenario:location="26883"/>
  <scenario:civilian scenario:location="34372"/>
  <scenario:civilian scenario:location="32213"/>
  <scenario:civilian scenario:location="36440"/>
  <scenario:civilian scenario:location="24570"/>
  <scenario:civilian scenario:location="20209"/>
  <scenario:civilian scenario:location="20633"/>
  <scenario:civilian scenario:location="24118"/>
  <scenario:civilian scenario:location="19386"/>
  <scenario:civilian scenario:location="36267"/>
  <scenario:civilian scenario:location="23905"/>
  <scenario:civilian scenario:location="21565"/>
  <scenario:civilian scenario:location="20633"/>
  <scenario:civilian scenario:location="36275"/>
  <scenario:civilian scenario:location="36556"/>
  <scenario:civilian scenario:location="35410"/>
  <scenario:civilian scenario:location="34884"/>
  <scenario:civilian scenario:location="31803"/>
  <scenario:civilian scenario:location="19507"/>
  <scenario:civilian scenario:location="36235"/>
  <scenario:civilian scenario:location="24430"/>
  <scenario:civilian scenario:location="36470"/>
  <scenario:civilian scenario:location="27375"/>
  <scenario:civilian scenario:location="19082"/>
  <scenario:civilian scenario:location="36215"/>
  <scenario:civilian scenario:location="23859"/>
  <scenario:civilian scenario:location="17030"/>
  <scenario:civilian scenario:location="24478"/>
  <scenario:civilian scenario:location="17783"/>
  <scenario:civilian scenario:location="28699"/>
  <scenario:civilian scenario:location="36491"/>
  <scenario:civilian scenario:location="36557"/>
  <scenario:civilian scenario:location="21970"/>
  <scenario:civilian scenario:location="20986"/>
  <scenario:civilian scenario:location="28463"/>
  <scenario:civilian scenario:location="36234"/>
  <scenario:civilian scenario:location="32774"/>
  <scenario:civilian scenario:location="21216"/>
  <scenario:civilian scenario:location="31494"/>
  <scenario:civilian scenario:location="29357"/>
  <scenario:civilian scenario:location="30393"/>
  <scenario:civilian scenario:location="36209"/>
  <scenario:civilian scenario:location="18293"/>
  <scenario:civilian scenario:location="21124"/>
  <scenario:civilian scenario:location="25970"/>
  <scenario:civilian scenario:location="36123"/>
  <scenario:civilian scenario:location="32751"/>
  <scenario:civilian scenario:location="36242"/>
  <scenario:civilian scenario:location="28024"/>
  <scenario:civilian scenario:location="36239"/>
  <scenario:civilian scenario:location="35269"/>
  <scenario:civilian scenario:location="27514"/>
  <scenario:civilian scenario:location="17322"/>
  <scenario:civilian scenario:location="29766"/>
  <scenario:civilian scenario:location="28699"/>
  <scenario:civilian scenario:location="36532"/>
  <scenario:civilian scenario:location="22855"/>
  <scenario:civilian scenario:location="26953"/>
  <scenario:civilian scenario:location="31078"/>
  <scenario:civilian scenario:location="27932"/>
  <scenario:civilian scenario:location="17760"/>
  <scenario:civilian scenario:location="30225"/>
  <scenario:civilian scenario:location="27794"/>
  <scenario:civilian scenario:location="36406"/>
  <scenario:civilian scenario:location="22146"/>
  <scenario:civilian scenario:location="36216"/>
  <scenario:civilian scenario:location="36442"/>
  <scenario:civilian scenario:location="33766"/>
  <scenario:civilian scenario:location="29836"/>
  <scenario:civilian scenario:location="30443"/>
  <scenario:civilian scenario:location="20940"/>
  <scenario:civilian scenario:location="26883"/>
  <scenario:civilian scenario:location="36405"/>
  <scenario:civilian scenario:location="30655"/>
  <scenario:civilian scenario:location="26930"/>
  <scenario:civilian scenario:location="29836"/>
  <scenario:civilian scenario:location="23168"/>
  <scenario:civilian scenario:location="28099"/>
  <scenario:civilian scenario:location="31101"/>
  <scenario:civilian scenario:location="22169"/>
  <scenario:civilian scenario:location="34464"/>
  <scenario:civilian scenario:location="19730"/>
  <scenario:civilian scenario:location="35484"/>
  <scenario:civilian scenario:location="22806"/>
  <scenario:civilian scenario:location="30443"/>
  <scenario:civilian scenario:location="28818"/>
  <scenario:civilian scenario:location="17737"/>
  <scenario:civilian scenario:location="36535"/>
  <scenario:civilian scenario:location="32705"/>
  <scenario:civilian scenario:location="31994"/>
  <scenario:civilian scenario:location="21193"/>
  <scenario:civilian scenario:location="30297"/>
  <scenario:civilian scenario:location="36491"/>
  <scenario:civilian scenario:location="33475"/>
  <scenario:civilian scenario:location="32017"/>
  <scenario:civilian scenario:location="19059"/>
  <scenario:civilian scenario:location="30773"/>
  <scenario:civilian scenario:location="35079"/>
  <scenario:civilian scenario:location="26016"/>
  <scenario:civilian scenario:location="36267"/>
  <scenario:civilian scenario:location="36460"/>
  <scenario:civilian scenario:location="24072"/>
  <scenario:civilian scenario:location="28099"/>
  <scenario:civilian scenario:location="18869"/>
  <scenario:civilian scenario:location="36517"/>
  <scenario:civilian scenario:location="34349"/>
  <scenario:civilian scenario:location="18440"/>
  <scenario:civilian scenario:location="18126"/>
  <scenario:civilian scenario:location="21517"/>
  <scenario:civilian scenario:location="30514"/>
  <scenario:civilian scenario:location="36497"/>
  <scenario:civilian scenario:location="19484"/>
  <scenario:civilian scenario:location="36495"/>
  <scenario:civilian scenario:location="36199"/>
  <scenario:civilian scenario:location="19681"/>
  <scenario:civilian scenario:location="36100"/>
  <scenario:civilian scenario:location="33444"/>
  <scenario:firebrigade scenario:location="10840"/>
  <scenario:firebrigade scenario:location="17053"/>
  <scenario:firebrigade scenario:location="17772"/>
  <scenario:firebrigade scenario:location="27549"/>
  <scenario:firebrigade scenario:location="3218"/>
  <scenario:firebrigade scenario:location="36252"/>
  <scenario:firebrigade scenario:location="8419"/>
  <scenario:firebrigade scenario:location="9364"/>
  <scenario:firebrigade scenario:location="9535"/>
  <scenario:firebrigade scenario:location="16681"/>
  <scenario:firebrigade scenario:location="7015"/>
  <scenario:firebrigade scenario:location="2077"/>
  <scenario:firebrigade scenario:location="9175"/>
  <scenario:firebrigade scenario:location="9076"/>
  <scenario:firebrigade scenario:location="10633"/>
  <scenario:firebrigade scenario:location="8554"/>
  <scenario:firebrigade scenario:location="6475"/>
  <scenario:firebrigade scenario:location="3514"/>
  <scenario:firebrigade scenario:location="10174"/>
  <scenario:firebrigade scenario:location="14665"/>
  <scenario:firebrigade scenario:location="10741"/>
  <scenario:firebrigade scenario:location="3781"/>
  <scenario:firebrigade scenario:location="7537"/>
  <scenario:firebrigade scenario:location="7555"/>
  <scenario:firebrigade scenario:location="12919"/>
  <scenario:firebrigade scenario:location="8545"/>
  <scenario:firebrigade scenario:location="280"/>
  <scenario:firebrigade scenario:location="7411"/>
  <scenario:firebrigade scenario:location="7384"/>
  <scenario:firebrigade scenario:location="7546"/>
  <scenario:firebrigade scenario:location="7546"/>
  <scenario:firebrigade scenario:location="14890"/>
  <scenario:firebrigade scenario:location="14890"/>
  <scenario:firebrigade scenario:location="14890"/>
  <scenario:firebrigade scenario:location="14899"/>
  <scenario:firebrigade scenario:location="14899"/>
  <scenario:firebrigade scenario:location="2858"/>
  <scenario:firebrigade scenario:location="8536"/>
  <scenario:firebrigade scenario:location="8545"/>
  <scenario:firestation scenario:location="35507"/>
  <scenario:firestation scenario:location="33766"/>
  <scenario:firestation scenario:location="31152"/>
  <scenario:policeforce scenario:location="10399"/>
  <scenario:policeforce scenario:location="32901"/>
  <scenario:policeforce scenario:location="13387"/>
  <scenario:policeforce scenario:location="4114"/>
  <scenario:policeforce scenario:location="26383"/>
  <scenario:policeforce scenario:location="28757"/>
  <scenario:policeforce scenario:location="5190"/>
  <scenario:policeforce scenario:location="4079"/>
  <scenario:policeforce scenario:location="6763"/>
  <scenario:policeforce scenario:location="6339"/>
  <scenario:policeforce scenario:location="29091"/>
  <scenario:policeforce scenario:location="36443"/>
  <scenario:policeforce scenario:location="21844"/>
  <scenario:policeforce scenario:location="24153"/>
  <scenario:policeforce scenario:location="33139"/>
  <scenario:policeforce scenario:location="11164"/>
  <scenario:policeforce scenario:location="11011"/>
  <scenario:policeforce scenario:location="10345"/>
  <scenario:policeforce scenario:location="9193"/>
  <scenario:policeforce scenario:location="8914"/>
  <scenario:policeforce scenario:location="11191"/>
  <scenario:policeforce scenario:location="7033"/>
  <scenario:policeforce scenario:location="8239"/>
  <scenario:policeforce scenario:location="2765"/>
  <scenario:policeforce scenario:location="10237"/>
  <scenario:policeforce scenario:location="11236"/>
  <scenario:policeforce scenario:location="11254"/>
  <scenario:policeforce scenario:location="10327"/>
  <scenario:policeforce scenario:location="16681"/>
  <scenario:policeforce scenario:location="11497"/>
  <scenario:policeforce scenario:location="11866"/>
  <scenario:policeforce scenario:location="12604"/>
  <scenario:policeforce scenario:location="12613"/>
  <scenario:policeforce scenario:location="16519"/>
  <scenario:policeforce scenario:location="12622"/>
  <scenario:policeforce scenario:location="10273"/>
  <scenario:policeforce scenario:location="13882"/>
  <scenario:policeforce scenario:location="32134"/>
  <scenario:policeforce scenario:location="13909"/>
  <scenario:policeoffice scenario:location="16800"/>
  <scenario:ambulanceteam scenario:location="8878"/>
  <scenario:ambulanceteam scenario:location="32866"/>
  <scenario:ambulanceteam scenario:location="12289"/>
  <scenario:ambulanceteam scenario:location="25576"/>
  <scenario:ambulanceteam scenario:location="22893"/>
  <scenario:ambulanceteam scenario:location="9499"/>
  <scenario:ambulanceteam scenario:location="18392"/>
  <scenario:ambulanceteam scenario:location="34700"/>
  <scenario:ambulanceteam scenario:location="8095"/>
  <scenario:ambulanceteam scenario:location="4900"/>
  <scenario:ambulanceteam scenario:location="34643"/>
  <scenario:ambulanceteam scenario:location="14917"/>
  <scenario:ambulanceteam scenario:location="12037"/>
  <scenario:ambulanceteam scenario:location="33587"/>
  <scenario:ambulanceteam scenario:location="19730"/>
  <scenario:ambulanceteam scenario:location="19840"/>
  <scenario:ambulanceteam scenario:location="17749"/>
  <scenario:ambulanceteam scenario:location="12973"/>
  <scenario:ambulanceteam scenario:location="7303"/>
  <scenario:ambulanceteam scenario:location="2059"/>
  <scenario:ambulanceteam scenario:location="8131"/>
  <scenario:ambulanceteam scenario:location="14053"/>
  <scenario:ambulanceteam scenario:location="4934"/>
  <scenario:ambulanceteam scenario:location="1808"/>
  <scenario:ambulanceteam scenario:location="10840"/>
  <scenario:ambulanceteam scenario:location="10489"/>
  <scenario:ambulanceteam scenario:location="10489"/>
  <scenario:ambulanceteam scenario:location="11992"/>
  <scenario:ambulanceteam scenario:location="16213"/>
  <scenario:ambulanceteam scenario:location="16222"/>
  <scenario:ambulancecentre scenario:location="19557"/>
  <scenario:ambulancecentre scenario:location="34769"/>
</scenario:scenario>
